{
  "tentit": [
    {
      "id": 1,
      "tentti": "Testi"
    },
    {
      "tentti": "Kannat 1",
      "kysymykset": [],
      "id": 2
    },
    {
      "tentti": "kannat 2",
      "kysymykset": [],
      "id": 3
    },
    {
      "tentti": "pÄIVITYKSET",
      "kysymykset": [],
      "id": 4
    },
    {
      "tentti": "Korjaukset",
      "kysymykset": [],
      "id": 5
    },
    {
      "tentti": "Rendauksesta",
      "kysymykset": [],
      "id": 6
    },
    {
      "tentti": "Rendaus 2",
      "kysymykset": [],
      "id": 7
    },
    {
      "tentti": "aaralliset",
      "kysymykset": [],
      "id": 8
    },
    {
      "tentti": "aaralliset",
      "kysymykset": [],
      "id": 9
    },
    {
      "tentti": "Vaaralliset",
      "kysymykset": [],
      "id": 10
    },
    {
      "tentti": "Toimivuus",
      "kysymykset": [],
      "id": 11
    },
    {
      "tentti": "Toimivuus 2",
      "kysymykset": [],
      "id": 12
    },
    {
      "tentti": "lopputentti",
      "kysymykset": [],
      "id": 13
    },
    {
      "tentti": "yks viel",
      "kysymykset": [],
      "id": 14
    },
    {
      "tentti": "promiseja 1",
      "kysymykset": [],
      "id": 15
    },
    {
      "tentti": "promiset 2",
      "kysymykset": [],
      "id": 16
    },
    {
      "tentti": "promiset 3",
      "kysymykset": [],
      "id": 17
    },
    {
      "tentti": "promiiseja 4",
      "kysymykset": [],
      "id": 18
    },
    {
      "tentti": "promiseja 5",
      "kysymykset": [],
      "id": 19
    },
    {
      "tentti": "paluufunktiot 1",
      "kysymykset": [],
      "id": 20
    },
    {
      "tentti": "paluufunktiot 2",
      "kysymykset": [],
      "id": 21
    },
    {
      "tentti": "paluufunktiot 3",
      "kysymykset": [],
      "id": 22
    },
    {
      "tentti": "paluut 4",
      "kysymykset": [],
      "id": 23
    },
    {
      "tentti": "paluut 5",
      "kysymykset": [],
      "id": 24
    },
    {
      "tentti": "paluut 6",
      "kysymykset": [],
      "id": 25
    }
  ]
}